README.rst
setup.py
pepa/__init__.py
pepa.egg-info/PKG-INFO
pepa.egg-info/SOURCES.txt
pepa.egg-info/dependency_links.txt
pepa.egg-info/requires.txt
pepa.egg-info/top_level.txt
scripts/pepa
scripts/pepa-test