Metadata-Version: 1.1
Name: pepa
Version: 0.8.1
Summary: Configuration templating for SaltStack using Hierarchical substitution and Jinja
Home-page: https://github.com/mickep76/pepa.git
Author: Michael Persson
Author-email: michael.ake.persson@gmail.com
License: Apache License, Version 2.0
Platform: UNKNOWN
Classifier: Development Status :: 5 - Production/Stable
Classifier: Environment :: Console
Classifier: Intended Audience :: System Administrators
Classifier: License :: OSI Approved :: Apache Software License
Classifier: Operating System :: POSIX :: Linux
